{
  "$schema": "https://developer.microsoft.com/json-schemas/fabric/item/report/definition/visualContainer/1.6.0/schema.json",
  "name": "1f5fb3334a3985903dd8",
  "position": {
    "x": 435.2238805970149,
    "y": 155.82089552238804,
    "z": 9000,
    "height": 260.59701492537312,
    "width": 410.14925373134326,
    "tabOrder": 9000
  },
  "visual": {
    "visualType": "donutChart",
    "query": {
      "queryState": {
        "Category": {
          "projections": [
            {
              "field": {
                "Column": {
                  "Expression": {
                    "SourceRef": {
                      "Entity": "vwdimSalesOrg"
                    }
                  },
                  "Property": "RegionName"
                }
              },
              "queryRef": "vwdimSalesOrg.RegionName",
              "nativeQueryRef": "Region",
              "active": true,
              "displayName": "Region"
            }
          ]
        },
        "Tooltips": {
          "projections": [
            {
              "field": {
                "Measure": {
                  "Expression": {
                    "SourceRef": {
                      "Entity": "vwFactSalesDashboardRev"
                    }
                  },
                  "Property": "Last Year Rev"
                }
              },
              "queryRef": "vwFactSalesDashboardRev.Last Year Rev",
              "nativeQueryRef": "Prior Period Revenue",
              "displayName": "Prior Period Revenue"
            }
          ]
        },
        "Y": {
          "projections": [
            {
              "field": {
                "Measure": {
                  "Expression": {
                    "SourceRef": {
                      "Entity": "vwFactSalesDashboardRev"
                    }
                  },
                  "Property": "Current Year Rev"
                }
              },
              "queryRef": "vwFactSalesDashboardRev.Current Year Rev",
              "nativeQueryRef": "Current Period Revenue",
              "displayName": "Current Period Revenue"
            }
          ]
        }
      },
      "sortDefinition": {
        "sort": [
          {
            "field": {
              "Measure": {
                "Expression": {
                  "SourceRef": {
                    "Entity": "vwFactSalesDashboardRev"
                  }
                },
                "Property": "Current Year Rev"
              }
            },
            "direction": "Descending"
          }
        ],
        "isDefaultSort": true
      }
    },
    "objects": {
      "dataPoint": [
        {
          "properties": {
            "fill": {
              "solid": {
                "color": {
                  "expr": {
                    "ThemeDataColor": {
                      "ColorId": 4,
                      "Percent": 0.6
                    }
                  }
                }
              }
            }
          },
          "selector": {
            "metadata": "vwFactSalesDashboardRev.Current Year Rev"
          }
        },
        {
          "properties": {
            "fill": {
              "solid": {
                "color": {
                  "expr": {
                    "ThemeDataColor": {
                      "ColorId": 4,
                      "Percent": -0.25
                    }
                  }
                }
              }
            }
          },
          "selector": {
            "metadata": "vwFactSalesDashboardRev.Last Year Rev"
          }
        }
      ],
      "labels": [
        {
          "properties": {
            "labelStyle": {
              "expr": {
                "Literal": {
                  "Value": "'Both'"
                }
              }
            }
          }
        }
      ]
    },
    "visualContainerObjects": {
      "title": [
        {
          "properties": {
            "text": {
              "expr": {
                "Literal": {
                  "Value": "'Revenue by Region'"
                }
              }
            }
          }
        }
      ]
    },
    "drillFilterOtherVisuals": true
  }
}