{
  "$schema": "https://developer.microsoft.com/json-schemas/fabric/item/report/definition/visualContainer/1.6.0/schema.json",
  "name": "6fb4cce1d33495c8e7a5",
  "position": {
    "x": 652.09448818897636,
    "y": 62.488188976377955,
    "z": 12000,
    "height": 65.511811023622045,
    "width": 244.91338582677164,
    "tabOrder": 12000
  },
  "visual": {
    "visualType": "slicer",
    "query": {
      "queryState": {
        "Values": {
          "projections": [
            {
              "field": {
                "Column": {
                  "Expression": {
                    "SourceRef": {
                      "Entity": "vwdimSalesOrg"
                    }
                  },
                  "Property": "SL_Account_Name"
                }
              },
              "queryRef": "vwdimSalesOrg.SL_Account_Name",
              "nativeQueryRef": "BICP Customer Channel",
              "active": true,
              "displayName": "BICP Customer Channel"
            }
          ]
        }
      }
    },
    "objects": {
      "general": [
        {
          "properties": {
            "selfFilterEnabled": {
              "expr": {
                "Literal": {
                  "Value": "true"
                }
              }
            }
          }
        }
      ]
    },
    "syncGroup": {
      "groupName": "SL_Account_Name",
      "fieldChanges": true,
      "filterChanges": true
    },
    "drillFilterOtherVisuals": true
  }
}