{
  "$schema": "https://developer.microsoft.com/json-schemas/fabric/item/report/definition/visualContainer/1.6.0/schema.json",
  "name": "f4db285070c4a3b2d758",
  "position": {
    "x": 0,
    "y": 0,
    "z": 1000,
    "height": 85.669291338582681,
    "width": 173.35433070866142,
    "tabOrder": 1000
  },
  "visual": {
    "visualType": "textbox",
    "objects": {
      "general": [
        {
          "properties": {
            "paragraphs": [
              {
                "textRuns": [
                  {
                    "value": "Revenue by Plant",
                    "textStyle": {
                      "fontWeight": "bold",
                      "fontSize": "16pt"
                    }
                  }
                ]
              },
              {
                "textRuns": [
                  {
                    "value": "*US Dollars Only",
                    "textStyle": {
                      "fontWeight": "bold",
                      "fontSize": "8pt"
                    }
                  }
                ]
              }
            ]
          }
        }
      ]
    },
    "drillFilterOtherVisuals": true
  }
}